chat_message/__init__.py
chat_message/example.py
chat_message/frontend/build/asset-manifest.json
chat_message/frontend/build/bootstrap.min.css
chat_message/frontend/build/index.html
chat_message/frontend/build/static/css/main.ba52fc6a.css
chat_message/frontend/build/static/css/main.ba52fc6a.css.map
chat_message/frontend/build/static/js/main.b2c352b9.js
chat_message/frontend/build/static/js/main.b2c352b9.js.LICENSE.txt
chat_message/frontend/build/static/js/main.b2c352b9.js.map
chat_message-1.0.0.dist-info/LICENSE
chat_message-1.0.0.dist-info/METADATA
chat_message-1.0.0.dist-info/WHEEL
chat_message-1.0.0.dist-info/top_level.txt
chat_message-1.0.0.dist-info/RECORD
