Metadata-Version: 2.1
Name: chat-message
Version: 1.0.0
Summary: Streamlit component that styles a chat bubble.
Home-page: UNKNOWN
Author: Jason O'Neal
Author-email: jason.allen.oneal@gmail.com
License: UNKNOWN
Platform: UNKNOWN
Requires-Python: >=3.7
Requires-Dist: streamlit >=0.63
Provides-Extra: devel
Requires-Dist: playwright ==1.39.0 ; extra == 'devel'
Requires-Dist: pytest-playwright-snapshot ==1.0 ; extra == 'devel'
Requires-Dist: pytest-rerunfailures ==12.0 ; extra == 'devel'
Requires-Dist: pytest ==7.4.0 ; extra == 'devel'
Requires-Dist: requests ==2.31.0 ; extra == 'devel'
Requires-Dist: wheel ; extra == 'devel'
